protoc_polyglot/__init__.py
protoc_polyglot/cli.py
protoc_polyglot/common_interface.py
protoc_polyglot/settings.py
protoc_polyglot/tools.py
protoc_polyglot/cpp/__init__.py
protoc_polyglot/cpp/language_interface.py
protoc_polyglot/csharp/__init__.py
protoc_polyglot/csharp/language_interface.py
protoc_polyglot/go/__init__.py
protoc_polyglot/go/language_interface.py
protoc_polyglot/java/__init__.py
protoc_polyglot/java/language_interface.py
protoc_polyglot/js/__init__.py
protoc_polyglot/js/language_interface.py
protoc_polyglot/obj-c/__init__.py
protoc_polyglot/obj-c/language_interface.py
protoc_polyglot/php/__init__.py
protoc_polyglot/php/language_interface.py
protoc_polyglot/python/__init__.py
protoc_polyglot/python/language_interface.py
protoc_polyglot/ruby/__init__.py
protoc_polyglot/ruby/language_interface.py
protoc_polyglot/rust/__init__.py
protoc_polyglot/rust/language_interface.py
protoc_polyglot-0.0.1.post86.dist-info/METADATA
protoc_polyglot-0.0.1.post86.dist-info/WHEEL
protoc_polyglot-0.0.1.post86.dist-info/entry_points.txt
protoc_polyglot-0.0.1.post86.dist-info/RECORD
