Metadata-Version: 2.3
Name: protoc_polyglot
Version: 0.0.1.post86
Summary: Protoc wrapper for compilation into any language
Project-URL: Homepage, https://github.com/quantasoftcz/protoc-polyglot
Project-URL: Issues, https://protopolyglot.youtrack.cloud/issues
Author-email: Milan Pultar <milan.pultar@gmail.com>, Hugo Kunák <hkunak8@gmail.com>
License: MIT License
Classifier: License :: OSI Approved :: MIT License
Classifier: Operating System :: OS Independent
Classifier: Programming Language :: Python :: 3
Requires-Python: >=3.8
Requires-Dist: argparse
Requires-Dist: fire
Requires-Dist: pyyaml
Requires-Dist: requests
